repocheck.py
repocheck-1.0.0.dist-info/DESCRIPTION.rst
repocheck-1.0.0.dist-info/METADATA
repocheck-1.0.0.dist-info/RECORD
repocheck-1.0.0.dist-info/WHEEL
repocheck-1.0.0.dist-info/entry_points.txt
repocheck-1.0.0.dist-info/metadata.json
repocheck-1.0.0.dist-info/top_level.txt
