Metadata-Version: 2.0
Name: repocheck
Version: 1.0.0
Summary: Check the status of code repositories under a root directory.
Home-page: https://github.com/kynikos/repocheck
Author: Dario Giovannetti
Author-email: dev@dariogiovannetti.net
License: GPLv3+
Keywords: git repository
Platform: UNKNOWN
Classifier: Development Status :: 5 - Production/Stable
Classifier: Environment :: Console
Classifier: Intended Audience :: Developers
Classifier: Topic :: Software Development :: Version Control
Classifier: Topic :: Software Development :: Version Control :: Git
Classifier: License :: OSI Approved :: GNU General Public License v3 or later (GPLv3+)
Classifier: Programming Language :: Python :: 3
